AUTHORS.rst
CONTRIBUTING.rst
HISTORY.rst
MANIFEST.in
README.rst
pyproject.toml
setup.py
src/easy_aes/__init__.py
src/python_easy_aes.egg-info/PKG-INFO
src/python_easy_aes.egg-info/SOURCES.txt
src/python_easy_aes.egg-info/dependency_links.txt
src/python_easy_aes.egg-info/requires.txt
src/python_easy_aes.egg-info/top_level.txt