Metadata-Version: 2.1
Name: python-easy-aes
Version: 1.0.0
Summary: Easily encrypt/decrypt files/texts using AES
Home-page: https://github.com/AriaBagheri/python_easy_aes
Author-email: Aria Bagheri <ariab9342@gmail.com>
License: UNKNOWN
Project-URL: Homepage, https://github.com/AriaBagheri/python_easy_aes
Keywords: python,AES,AES-256
Platform: UNKNOWN
Classifier: License :: OSI Approved :: MIT License
Classifier: Programming Language :: Python
Classifier: Programming Language :: Python :: 3
Requires-Python: >=3.9
License-File: AUTHORS.rst
